belial_backend/__about__.py
belial_backend/__init__.py
belial_backend/database.py
belial_backend/api/__init__.py
belial_backend/api/assets.py
belial_backend/schemas/__init__.py
belial_backend/schemas/asset.py
belial_backend/schemas/vector_3.py
belial_backend/schemas/vector_4.py
manmade2_belialbackend-1.0.0.dist-info/METADATA
manmade2_belialbackend-1.0.0.dist-info/WHEEL
manmade2_belialbackend-1.0.0.dist-info/licenses/LICENSE.txt
manmade2_belialbackend-1.0.0.dist-info/RECORD
